<?xml version="1.0" encoding="ISO-8859-1"?>
<sculpture>
	<elements>
		<element id="0">
			<motors>
				<motor id="0">
					<position x="0.0" y="0.0" z="0.0"/>
					<connectionPosition x="0.0" y="0.0" z="0.0"/>
				</motor>
				<motor id="0">
					<position x="0.0" y="0.0" z="0.0"/>
					<connectionPosition x="0.0" y="0.0" z="0.0"/>
				</motor>
				<bounds/>
				<centroid x="0.0" y="0.0" z="0.0"/>
			</motors>
			<lights/>
			<matrix m00="1.0" m01="0.0" m02="0.0" m03="0.0" m10="0.0" m11="1.0" m12="0.0" m13="0.0" m20="0.0" m21="0.0" m22="1.0" m23="0.0" m30="-200.0" m31="-200.0" m32="0.0" m33="1.0"/>
		</element>
		<element id="1">
			<motors>
				<motor id="1">
					<position x="0.0" y="0.0" z="0.0"/>
					<connectionPosition x="0.0" y="0.0" z="0.0"/>
				</motor>
				<motor id="1">
					<position x="0.0" y="0.0" z="0.0"/>
					<connectionPosition x="0.0" y="0.0" z="0.0"/>
				</motor>
				<bounds/>
				<centroid x="0.0" y="0.0" z="0.0"/>
			</motors>
			<lights/>
			<matrix m00="1.0" m01="0.0" m02="0.0" m03="0.0" m10="0.0" m11="1.0" m12="0.0" m13="0.0" m20="0.0" m21="0.0" m22="1.0" m23="0.0" m30="-200.0" m31="-100.0" m32="0.0" m33="1.0"/>
		</element>
		<element id="2">
			<motors>
				<motor id="2">
					<position x="0.0" y="0.0" z="0.0"/>
					<connectionPosition x="0.0" y="0.0" z="0.0"/>
				</motor>
				<motor id="2">
					<position x="0.0" y="0.0" z="0.0"/>
					<connectionPosition x="0.0" y="0.0" z="0.0"/>
				</motor>
				<bounds/>
				<centroid x="0.0" y="0.0" z="0.0"/>
			</motors>
			<lights/>
			<matrix m00="1.0" m01="0.0" m02="0.0" m03="0.0" m10="0.0" m11="1.0" m12="0.0" m13="0.0" m20="0.0" m21="0.0" m22="1.0" m23="0.0" m30="-200.0" m31="0.0" m32="0.0" m33="1.0"/>
		</element>
		<element id="3">
			<motors>
				<motor id="3">
					<position x="0.0" y="0.0" z="0.0"/>
					<connectionPosition x="0.0" y="0.0" z="0.0"/>
				</motor>
				<motor id="3">
					<position x="0.0" y="0.0" z="0.0"/>
					<connectionPosition x="0.0" y="0.0" z="0.0"/>
				</motor>
				<bounds/>
				<centroid x="0.0" y="0.0" z="0.0"/>
			</motors>
			<lights/>
			<matrix m00="1.0" m01="0.0" m02="0.0" m03="0.0" m10="0.0" m11="1.0" m12="0.0" m13="0.0" m20="0.0" m21="0.0" m22="1.0" m23="0.0" m30="-200.0" m31="100.0" m32="0.0" m33="1.0"/>
		</element>
		<element id="4">
			<motors>
				<motor id="4">
					<position x="0.0" y="0.0" z="0.0"/>
					<connectionPosition x="0.0" y="0.0" z="0.0"/>
				</motor>
				<motor id="4">
					<position x="0.0" y="0.0" z="0.0"/>
					<connectionPosition x="0.0" y="0.0" z="0.0"/>
				</motor>
				<bounds/>
				<centroid x="0.0" y="0.0" z="0.0"/>
			</motors>
			<lights/>
			<matrix m00="1.0" m01="0.0" m02="0.0" m03="0.0" m10="0.0" m11="1.0" m12="0.0" m13="0.0" m20="0.0" m21="0.0" m22="1.0" m23="0.0" m30="-200.0" m31="200.0" m32="0.0" m33="1.0"/>
		</element>
		<element id="5">
			<motors>
				<motor id="5">
					<position x="0.0" y="0.0" z="0.0"/>
					<connectionPosition x="0.0" y="0.0" z="0.0"/>
				</motor>
				<motor id="5">
					<position x="0.0" y="0.0" z="0.0"/>
					<connectionPosition x="0.0" y="0.0" z="0.0"/>
				</motor>
				<bounds/>
				<centroid x="0.0" y="0.0" z="0.0"/>
			</motors>
			<lights/>
			<matrix m00="1.0" m01="0.0" m02="0.0" m03="0.0" m10="0.0" m11="1.0" m12="0.0" m13="0.0" m20="0.0" m21="0.0" m22="1.0" m23="0.0" m30="-100.0" m31="-200.0" m32="0.0" m33="1.0"/>
		</element>
		<element id="6">
			<motors>
				<motor id="6">
					<position x="0.0" y="0.0" z="0.0"/>
					<connectionPosition x="0.0" y="0.0" z="0.0"/>
				</motor>
				<motor id="6">
					<position x="0.0" y="0.0" z="0.0"/>
					<connectionPosition x="0.0" y="0.0" z="0.0"/>
				</motor>
				<bounds/>
				<centroid x="0.0" y="0.0" z="0.0"/>
			</motors>
			<lights/>
			<matrix m00="1.0" m01="0.0" m02="0.0" m03="0.0" m10="0.0" m11="1.0" m12="0.0" m13="0.0" m20="0.0" m21="0.0" m22="1.0" m23="0.0" m30="-100.0" m31="-100.0" m32="0.0" m33="1.0"/>
		</element>
		<element id="7">
			<motors>
				<motor id="7">
					<position x="0.0" y="0.0" z="0.0"/>
					<connectionPosition x="0.0" y="0.0" z="0.0"/>
				</motor>
				<motor id="7">
					<position x="0.0" y="0.0" z="0.0"/>
					<connectionPosition x="0.0" y="0.0" z="0.0"/>
				</motor>
				<bounds/>
				<centroid x="0.0" y="0.0" z="0.0"/>
			</motors>
			<lights/>
			<matrix m00="1.0" m01="0.0" m02="0.0" m03="0.0" m10="0.0" m11="1.0" m12="0.0" m13="0.0" m20="0.0" m21="0.0" m22="1.0" m23="0.0" m30="-100.0" m31="0.0" m32="0.0" m33="1.0"/>
		</element>
		<element id="8">
			<motors>
				<motor id="8">
					<position x="0.0" y="0.0" z="0.0"/>
					<connectionPosition x="0.0" y="0.0" z="0.0"/>
				</motor>
				<motor id="8">
					<position x="0.0" y="0.0" z="0.0"/>
					<connectionPosition x="0.0" y="0.0" z="0.0"/>
				</motor>
				<bounds/>
				<centroid x="0.0" y="0.0" z="0.0"/>
			</motors>
			<lights/>
			<matrix m00="1.0" m01="0.0" m02="0.0" m03="0.0" m10="0.0" m11="1.0" m12="0.0" m13="0.0" m20="0.0" m21="0.0" m22="1.0" m23="0.0" m30="-100.0" m31="100.0" m32="0.0" m33="1.0"/>
		</element>
		<element id="9">
			<motors>
				<motor id="9">
					<position x="0.0" y="0.0" z="0.0"/>
					<connectionPosition x="0.0" y="0.0" z="0.0"/>
				</motor>
				<motor id="9">
					<position x="0.0" y="0.0" z="0.0"/>
					<connectionPosition x="0.0" y="0.0" z="0.0"/>
				</motor>
				<bounds/>
				<centroid x="0.0" y="0.0" z="0.0"/>
			</motors>
			<lights/>
			<matrix m00="1.0" m01="0.0" m02="0.0" m03="0.0" m10="0.0" m11="1.0" m12="0.0" m13="0.0" m20="0.0" m21="0.0" m22="1.0" m23="0.0" m30="-100.0" m31="200.0" m32="0.0" m33="1.0"/>
		</element>
		<element id="10">
			<motors>
				<motor id="10">
					<position x="0.0" y="0.0" z="0.0"/>
					<connectionPosition x="0.0" y="0.0" z="0.0"/>
				</motor>
				<motor id="10">
					<position x="0.0" y="0.0" z="0.0"/>
					<connectionPosition x="0.0" y="0.0" z="0.0"/>
				</motor>
				<bounds/>
				<centroid x="0.0" y="0.0" z="0.0"/>
			</motors>
			<lights/>
			<matrix m00="1.0" m01="0.0" m02="0.0" m03="0.0" m10="0.0" m11="1.0" m12="0.0" m13="0.0" m20="0.0" m21="0.0" m22="1.0" m23="0.0" m30="0.0" m31="-200.0" m32="0.0" m33="1.0"/>
		</element>
		<element id="11">
			<motors>
				<motor id="11">
					<position x="0.0" y="0.0" z="0.0"/>
					<connectionPosition x="0.0" y="0.0" z="0.0"/>
				</motor>
				<motor id="11">
					<position x="0.0" y="0.0" z="0.0"/>
					<connectionPosition x="0.0" y="0.0" z="0.0"/>
				</motor>
				<bounds/>
				<centroid x="0.0" y="0.0" z="0.0"/>
			</motors>
			<lights/>
			<matrix m00="1.0" m01="0.0" m02="0.0" m03="0.0" m10="0.0" m11="1.0" m12="0.0" m13="0.0" m20="0.0" m21="0.0" m22="1.0" m23="0.0" m30="0.0" m31="-100.0" m32="0.0" m33="1.0"/>
		</element>
		<element id="12">
			<motors>
				<motor id="12">
					<position x="0.0" y="0.0" z="0.0"/>
					<connectionPosition x="0.0" y="0.0" z="0.0"/>
				</motor>
				<motor id="12">
					<position x="0.0" y="0.0" z="0.0"/>
					<connectionPosition x="0.0" y="0.0" z="0.0"/>
				</motor>
				<bounds/>
				<centroid x="0.0" y="0.0" z="0.0"/>
			</motors>
			<lights/>
			<matrix m00="1.0" m01="0.0" m02="0.0" m03="0.0" m10="0.0" m11="1.0" m12="0.0" m13="0.0" m20="0.0" m21="0.0" m22="1.0" m23="0.0" m30="0.0" m31="0.0" m32="0.0" m33="1.0"/>
		</element>
		<element id="13">
			<motors>
				<motor id="13">
					<position x="0.0" y="0.0" z="0.0"/>
					<connectionPosition x="0.0" y="0.0" z="0.0"/>
				</motor>
				<motor id="13">
					<position x="0.0" y="0.0" z="0.0"/>
					<connectionPosition x="0.0" y="0.0" z="0.0"/>
				</motor>
				<bounds/>
				<centroid x="0.0" y="0.0" z="0.0"/>
			</motors>
			<lights/>
			<matrix m00="1.0" m01="0.0" m02="0.0" m03="0.0" m10="0.0" m11="1.0" m12="0.0" m13="0.0" m20="0.0" m21="0.0" m22="1.0" m23="0.0" m30="0.0" m31="100.0" m32="0.0" m33="1.0"/>
		</element>
		<element id="14">
			<motors>
				<motor id="14">
					<position x="0.0" y="0.0" z="0.0"/>
					<connectionPosition x="0.0" y="0.0" z="0.0"/>
				</motor>
				<motor id="14">
					<position x="0.0" y="0.0" z="0.0"/>
					<connectionPosition x="0.0" y="0.0" z="0.0"/>
				</motor>
				<bounds/>
				<centroid x="0.0" y="0.0" z="0.0"/>
			</motors>
			<lights/>
			<matrix m00="1.0" m01="0.0" m02="0.0" m03="0.0" m10="0.0" m11="1.0" m12="0.0" m13="0.0" m20="0.0" m21="0.0" m22="1.0" m23="0.0" m30="0.0" m31="200.0" m32="0.0" m33="1.0"/>
		</element>
		<element id="15">
			<motors>
				<motor id="15">
					<position x="0.0" y="0.0" z="0.0"/>
					<connectionPosition x="0.0" y="0.0" z="0.0"/>
				</motor>
				<motor id="15">
					<position x="0.0" y="0.0" z="0.0"/>
					<connectionPosition x="0.0" y="0.0" z="0.0"/>
				</motor>
				<bounds/>
				<centroid x="0.0" y="0.0" z="0.0"/>
			</motors>
			<lights/>
			<matrix m00="1.0" m01="0.0" m02="0.0" m03="0.0" m10="0.0" m11="1.0" m12="0.0" m13="0.0" m20="0.0" m21="0.0" m22="1.0" m23="0.0" m30="100.0" m31="-200.0" m32="0.0" m33="1.0"/>
		</element>
		<element id="16">
			<motors>
				<motor id="16">
					<position x="0.0" y="0.0" z="0.0"/>
					<connectionPosition x="0.0" y="0.0" z="0.0"/>
				</motor>
				<motor id="16">
					<position x="0.0" y="0.0" z="0.0"/>
					<connectionPosition x="0.0" y="0.0" z="0.0"/>
				</motor>
				<bounds/>
				<centroid x="0.0" y="0.0" z="0.0"/>
			</motors>
			<lights/>
			<matrix m00="1.0" m01="0.0" m02="0.0" m03="0.0" m10="0.0" m11="1.0" m12="0.0" m13="0.0" m20="0.0" m21="0.0" m22="1.0" m23="0.0" m30="100.0" m31="-100.0" m32="0.0" m33="1.0"/>
		</element>
		<element id="17">
			<motors>
				<motor id="17">
					<position x="0.0" y="0.0" z="0.0"/>
					<connectionPosition x="0.0" y="0.0" z="0.0"/>
				</motor>
				<motor id="17">
					<position x="0.0" y="0.0" z="0.0"/>
					<connectionPosition x="0.0" y="0.0" z="0.0"/>
				</motor>
				<bounds/>
				<centroid x="0.0" y="0.0" z="0.0"/>
			</motors>
			<lights/>
			<matrix m00="1.0" m01="0.0" m02="0.0" m03="0.0" m10="0.0" m11="1.0" m12="0.0" m13="0.0" m20="0.0" m21="0.0" m22="1.0" m23="0.0" m30="100.0" m31="0.0" m32="0.0" m33="1.0"/>
		</element>
		<element id="18">
			<motors>
				<motor id="18">
					<position x="0.0" y="0.0" z="0.0"/>
					<connectionPosition x="0.0" y="0.0" z="0.0"/>
				</motor>
				<motor id="18">
					<position x="0.0" y="0.0" z="0.0"/>
					<connectionPosition x="0.0" y="0.0" z="0.0"/>
				</motor>
				<bounds/>
				<centroid x="0.0" y="0.0" z="0.0"/>
			</motors>
			<lights/>
			<matrix m00="1.0" m01="0.0" m02="0.0" m03="0.0" m10="0.0" m11="1.0" m12="0.0" m13="0.0" m20="0.0" m21="0.0" m22="1.0" m23="0.0" m30="100.0" m31="100.0" m32="0.0" m33="1.0"/>
		</element>
		<element id="19">
			<motors>
				<motor id="19">
					<position x="0.0" y="0.0" z="0.0"/>
					<connectionPosition x="0.0" y="0.0" z="0.0"/>
				</motor>
				<motor id="19">
					<position x="0.0" y="0.0" z="0.0"/>
					<connectionPosition x="0.0" y="0.0" z="0.0"/>
				</motor>
				<bounds/>
				<centroid x="0.0" y="0.0" z="0.0"/>
			</motors>
			<lights/>
			<matrix m00="1.0" m01="0.0" m02="0.0" m03="0.0" m10="0.0" m11="1.0" m12="0.0" m13="0.0" m20="0.0" m21="0.0" m22="1.0" m23="0.0" m30="100.0" m31="200.0" m32="0.0" m33="1.0"/>
		</element>
		<element id="20">
			<motors>
				<motor id="20">
					<position x="0.0" y="0.0" z="0.0"/>
					<connectionPosition x="0.0" y="0.0" z="0.0"/>
				</motor>
				<motor id="20">
					<position x="0.0" y="0.0" z="0.0"/>
					<connectionPosition x="0.0" y="0.0" z="0.0"/>
				</motor>
				<bounds/>
				<centroid x="0.0" y="0.0" z="0.0"/>
			</motors>
			<lights/>
			<matrix m00="1.0" m01="0.0" m02="0.0" m03="0.0" m10="0.0" m11="1.0" m12="0.0" m13="0.0" m20="0.0" m21="0.0" m22="1.0" m23="0.0" m30="200.0" m31="-200.0" m32="0.0" m33="1.0"/>
		</element>
		<element id="21">
			<motors>
				<motor id="21">
					<position x="0.0" y="0.0" z="0.0"/>
					<connectionPosition x="0.0" y="0.0" z="0.0"/>
				</motor>
				<motor id="21">
					<position x="0.0" y="0.0" z="0.0"/>
					<connectionPosition x="0.0" y="0.0" z="0.0"/>
				</motor>
				<bounds/>
				<centroid x="0.0" y="0.0" z="0.0"/>
			</motors>
			<lights/>
			<matrix m00="1.0" m01="0.0" m02="0.0" m03="0.0" m10="0.0" m11="1.0" m12="0.0" m13="0.0" m20="0.0" m21="0.0" m22="1.0" m23="0.0" m30="200.0" m31="-100.0" m32="0.0" m33="1.0"/>
		</element>
		<element id="22">
			<motors>
				<motor id="22">
					<position x="0.0" y="0.0" z="0.0"/>
					<connectionPosition x="0.0" y="0.0" z="0.0"/>
				</motor>
				<motor id="22">
					<position x="0.0" y="0.0" z="0.0"/>
					<connectionPosition x="0.0" y="0.0" z="0.0"/>
				</motor>
				<bounds/>
				<centroid x="0.0" y="0.0" z="0.0"/>
			</motors>
			<lights/>
			<matrix m00="1.0" m01="0.0" m02="0.0" m03="0.0" m10="0.0" m11="1.0" m12="0.0" m13="0.0" m20="0.0" m21="0.0" m22="1.0" m23="0.0" m30="200.0" m31="0.0" m32="0.0" m33="1.0"/>
		</element>
		<element id="23">
			<motors>
				<motor id="23">
					<position x="0.0" y="0.0" z="0.0"/>
					<connectionPosition x="0.0" y="0.0" z="0.0"/>
				</motor>
				<motor id="23">
					<position x="0.0" y="0.0" z="0.0"/>
					<connectionPosition x="0.0" y="0.0" z="0.0"/>
				</motor>
				<bounds/>
				<centroid x="0.0" y="0.0" z="0.0"/>
			</motors>
			<lights/>
			<matrix m00="1.0" m01="0.0" m02="0.0" m03="0.0" m10="0.0" m11="1.0" m12="0.0" m13="0.0" m20="0.0" m21="0.0" m22="1.0" m23="0.0" m30="200.0" m31="100.0" m32="0.0" m33="1.0"/>
		</element>
		<element id="24">
			<motors>
				<motor id="24">
					<position x="0.0" y="0.0" z="0.0"/>
					<connectionPosition x="0.0" y="0.0" z="0.0"/>
				</motor>
				<motor id="24">
					<position x="0.0" y="0.0" z="0.0"/>
					<connectionPosition x="0.0" y="0.0" z="0.0"/>
				</motor>
				<bounds/>
				<centroid x="0.0" y="0.0" z="0.0"/>
			</motors>
			<lights/>
			<matrix m00="1.0" m01="0.0" m02="0.0" m03="0.0" m10="0.0" m11="1.0" m12="0.0" m13="0.0" m20="0.0" m21="0.0" m22="1.0" m23="0.0" m30="200.0" m31="200.0" m32="0.0" m33="1.0"/>
		</element>
	</elements>
</sculpture>